{
  "$schema": "http://json-schema.org/draft-07/schema#",
  "title": "JSON schema for i18n in View Exports SVG extension for Visual Studio Code",
  "type": "object",
  "properties": {
    "extensionTitle": {
      "type": "string",
      "description": "The title of the extension",
      "default": "View Exports SVG"
    },
    "iconExtractionInProgress": {
      "type": "string",
      "description": "Message displayed when icon extraction is in progress",
      "default": "Icon extraction in progress..."
    },
    "noIconsFound": {
      "type": "string",
      "description": "Message displayed when no icons are found",
      "default": "No icons found"
    },
    "noFileSelected": {
      "type": "string",
      "description": "Message displayed when no file is selected",
      "default": "No file selected"
    },
    "searchMinChars": {
      "type": "string",
      "description": "Message displayed when the search input has less than 3 characters",
      "default": "Please enter at least 3 characters to search..."
    },
    "noExistedFile": {
      "type": "string",
      "description": "Message displayed when a file does not exist",
      "default": "The file {file} does not exist.",
      "pattern": ".*\\{file\\}.*",
      "patternErrorMessage": "The message must contain the variable {file}"
    },
    "errorSettingWebviewMessageListener": {
      "type": "string",
      "description": "Message displayed when an error occurs setting the webview message listener",
      "default": "Error setting webview message listener"
    },
    "invalidSvgTag": {
      "type": "string",
      "description": "Message displayed when an invalid SVG tag is found",
      "default": "Invalid SVG tag: {tag}",
      "pattern": ".*\\{tag\\}.*",
      "patternErrorMessage": "The message must contain the variable {tag}"
    },
    "declarationNotFound": {
      "type": "string",
      "description": "Message displayed when a declaration is not found",
      "default": "Declaration named {name} not found in file {file}",
      "pattern": ".*\\{name\\}.*\\{file\\}.*|.*\\{file\\}.*\\{name\\}.*",
      "patternErrorMessage": "The message must contain the variables {name} and {file}"
    },
    "svgFileNotFound": {
      "type": "string",
      "description": "Message displayed when an SVG file is not found",
      "default": "SVG file {file} not found",
      "pattern": ".*\\{file\\}.*",
      "patternErrorMessage": "The message must contain the variable {file}"
    },
    "svgComponentNotFoundFile": {
      "type": "string",
      "description": "Message displayed when an SVG component is not found in a file",
      "default": "SVG component {name} not found in file {file}",
      "pattern": ".*\\{name\\}.*\\{file\\}.*|.*\\{file\\}.*\\{name\\}.*",
      "patternErrorMessage": "The message must contain the variables {name} and {file}"
    },
    "errorExtractingSvgComponent": {
      "type": "string",
      "description": "Message displayed when an error occurs extracting an SVG component",
      "default": "Error extracting SVG component {name}",
      "pattern": ".*\\{name\\}.*",
      "patternErrorMessage": "The message must contain the variable {name}"
    },
    "invalidAttribute": {
      "type": "string",
      "description": "Message displayed when an invalid attribute is found",
      "default": "Invalid {attr} attribute, expected '{expected}' but got {actual}",
      "pattern": ".*\\{attr\\}.*\\{expected\\}.*\\{actual\\}.*|.*\\{attr\\}.*\\{actual\\}.*\\{expected\\}.*|.*\\{expected\\}.*\\{attr\\}.*\\{actual\\}.*|.*\\{expected\\}.*\\{actual\\}.*\\{attr\\}.*|.*\\{actual\\}.*\\{attr\\}.*\\{expected\\}.*|.*\\{actual\\}.*\\{expected\\}.*\\{attr\\}.*",
      "patternErrorMessage": "The message must contain the variables {attr}, {expected}, and {actual}"
    },
    "errorScanningWorkspace": {
      "type": "string",
      "description": "Message displayed when an error occurs scanning the workspace",
      "default": "Error scanning workspace"
    },
    "errorScanningFiles": {
      "type": "string",
      "description": "Message displayed when an error occurs scanning files",
      "default": "Error scanning files"
    },
    "errorOpeningFile": {
      "type": "string",
      "description": "Message displayed when an error occurs opening a file",
      "default": "Error opening file {file} in editor",
      "pattern": ".*\\{file\\}.*",
      "patternErrorMessage": "The message must contain the variable {file}"
    },
    "errorSavingCache": {
      "type": "string",
      "description": "Message displayed when an error occurs saving the cache",
      "default": "Error saving cache"
    },
    "errorLoadingCache": {
      "type": "string",
      "description": "Message displayed when an error occurs loading the cache",
      "default": "Error loading cache"
    },
    "CacheManager has not been initialized": {
      "type": "string",
      "description": "Message displayed when the CacheManager has not been initialized",
      "default": "CacheManager has not been initialized."
    },
    "methodNotImplemented": {
      "type": "string",
      "description": "Message displayed when a method is not implemented",
      "default": "Method not implemented"
    }
  },
  "required": [
    "extensionTitle",
    "iconExtractionInProgress",
    "noIconsFound",
    "noFileSelected",
    "searchMinChars",
    "noExistedFile",
    "errorSettingWebviewMessageListener",
    "invalidSvgTag",
    "declarationNotFound",
    "svgFileNotFound",
    "svgComponentNotFoundFile",
    "errorExtractingSvgComponent",
    "invalidAttribute",
    "errorScanningWorkspace",
    "errorScanningFiles",
    "errorOpeningFile",
    "errorSavingCache",
    "errorLoadingCache",
    "CacheManager has not been initialized",
    "methodNotImplemented"
  ]
}
